nonebot_plugin_rrc/__init__.py
nonebot_plugin_rrc-0.0.6.dist-info/METADATA
nonebot_plugin_rrc-0.0.6.dist-info/WHEEL
nonebot_plugin_rrc-0.0.6.dist-info/top_level.txt
nonebot_plugin_rrc-0.0.6.dist-info/RECORD
