Metadata-Version: 2.1
Name: nonebot-plugin-rrc
Version: 0.0.6
Summary: 修仙插件
Home-page: https://github.com/QingMuCat/nonebot_plugin_rrc
Author: QingmuCat
Author-email: 1242550160@qq.com
Platform: any
Classifier: Programming Language :: Python :: 3
Classifier: License :: OSI Approved :: GNU General Public License v3 (GPLv3)
Classifier: Natural Language :: Chinese (Simplified)
Requires-Dist: fastapi
Requires-Dist: nonebot-adapter-onebot
Requires-Dist: nonebot2
